rustyzipper/__init__.py
rustyzipper/compat.py
rustyzipper/exceptions.py
rustyzipper/py.typed
rustyzipper/rustyzip.abi3.so
rustyzipper-1.1.0.dist-info/METADATA
rustyzipper-1.1.0.dist-info/WHEEL
rustyzipper-1.1.0.dist-info/licenses/LICENSE-APACHE
rustyzipper-1.1.0.dist-info/licenses/LICENSE-MIT
rustyzipper.libs/libgcc_s-f685abf1.so.1
rustyzipper-1.1.0.dist-info/RECORD
