Metadata-Version: 2.4
Name: rustyzipper
Version: 1.1.0
Classifier: Development Status :: 5 - Production/Stable
Classifier: Intended Audience :: Developers
Classifier: License :: OSI Approved :: MIT License
Classifier: License :: OSI Approved :: Apache Software License
Classifier: Operating System :: OS Independent
Classifier: Programming Language :: Python :: 3
Classifier: Programming Language :: Python :: 3.8
Classifier: Programming Language :: Python :: 3.9
Classifier: Programming Language :: Python :: 3.10
Classifier: Programming Language :: Python :: 3.11
Classifier: Programming Language :: Python :: 3.12
Classifier: Programming Language :: Python :: 3.13
Classifier: Programming Language :: Rust
Classifier: Topic :: System :: Archiving :: Compression
Classifier: Topic :: Security :: Cryptography
Classifier: Typing :: Typed
Requires-Dist: pytest>=7.0 ; extra == 'dev'
Requires-Dist: pytest-cov>=4.0 ; extra == 'dev'
Requires-Dist: black>=23.0 ; extra == 'dev'
Requires-Dist: mypy>=1.0 ; extra == 'dev'
Requires-Dist: ruff>=0.1 ; extra == 'dev'
Provides-Extra: dev
License-File: LICENSE-APACHE
License-File: LICENSE-MIT
Summary: A high-performance, secure file compression library with password protection
Keywords: zip,compression,encryption,aes,security,pyminizip
Author: RustyZip Contributors
License: MIT OR Apache-2.0
Requires-Python: >=3.8
Project-URL: Documentation, https://rustyzip.readthedocs.io
Project-URL: Homepage, https://github.com/johnnywale/rustyzip
Project-URL: Issues, https://github.com/johnnywale/rustyzip/issues
Project-URL: Repository, https://github.com/johnnywale/rustyzip
